.gitignore
MANIFEST.in
README.md
setup.cfg
setup.py
bubbler/__init__.py
bubbler.egg-info/PKG-INFO
bubbler.egg-info/SOURCES.txt
bubbler.egg-info/dependency_links.txt
bubbler.egg-info/top_level.txt
tests/.gitignore
tests/testBubbler.py