Metadata-Version: 1.0
Name: bubbler
Version: 0.1
Summary: Python Events
Home-page: https://github.com/basementcat/bubbler
Author: Alec Elton
Author-email: alec.elton@gmail.com
License: UNKNOWN
Platform: UNKNOWN
